<rootNode>
  <IsSuccess>false</IsSuccess>
  <ResponseMSG>The parameterized query '(@AutoVoucherNo int,@CostClassId int,@CurRate float,@CurrencyId ' expects the parameter '@AutoManualNo', which was not supplied.</ResponseMSG>
  <Data>
    <ResponseMSG>The parameterized query '(@AutoVoucherNo int,@CostClassId int,@CurRate float,@CurrencyId ' expects the parameter '@AutoManualNo', which was not supplied.</ResponseMSG>
    <IsSuccess>false</IsSuccess>
    <RId>0</RId>
    <CUserId>0</CUserId>
    <ResponseId />
    <EntityId>0</EntityId>
    <ErrorNumber>0</ErrorNumber>
  </Data>
  <TotalCount>0</TotalCount>
  <ContentEncoding />
  <ContentType />
  <JsonRequestBehavior>1</JsonRequestBehavior>
  <MaxJsonLength />
  <RecursionLimit />
</rootNode>