<rootNode>
  <IsSuccess>false</IsSuccess>
  <ResponseMSG>SqlDateTime overflow. Must be between 1/1/1753 12:00:00 AM and 12/31/9999 11:59:59 PM.</ResponseMSG>
  <Data>
    <ResponseMSG>SqlDateTime overflow. Must be between 1/1/1753 12:00:00 AM and 12/31/9999 11:59:59 PM.</ResponseMSG>
    <IsSuccess>false</IsSuccess>
    <RId>0</RId>
    <CUserId>0</CUserId>
    <ResponseId />
    <EntityId>0</EntityId>
    <ErrorNumber>0</ErrorNumber>
  </Data>
  <TotalCount>0</TotalCount>
  <ContentEncoding />
  <ContentType />
  <JsonRequestBehavior>1</JsonRequestBehavior>
  <MaxJsonLength />
  <RecursionLimit />
</rootNode>